MANIFEST.in
README.rst
setup.cfg
setup.py
docs/HISTORY.rst
docs/INSTALL.rst
docs/LICENSE.GPL
docs/LICENSE.txt
plonetheme/__init__.py
plonetheme.office.egg-info/PKG-INFO
plonetheme.office.egg-info/SOURCES.txt
plonetheme.office.egg-info/dependency_links.txt
plonetheme.office.egg-info/entry_points.txt
plonetheme.office.egg-info/namespace_packages.txt
plonetheme.office.egg-info/not-zip-safe
plonetheme.office.egg-info/paster_plugins.txt
plonetheme.office.egg-info/requires.txt
plonetheme.office.egg-info/top_level.txt
plonetheme/office/__init__.py
plonetheme/office/configure.zcml
plonetheme/office/interfaces.py
plonetheme/office/setuphandlers.py
plonetheme/office/browser/README.txt
plonetheme/office/browser/__init__.py
plonetheme/office/jbot/README.txt
plonetheme/office/locales/README.txt
plonetheme/office/profiles/default/browserlayer.xml
plonetheme/office/profiles/default/cssregistry.xml
plonetheme/office/profiles/default/jsregistry.xml
plonetheme/office/profiles/default/metadata.xml
plonetheme/office/profiles/default/plonetheme.office.marker.txt
plonetheme/office/profiles/default/registry.xml
plonetheme/office/profiles/default/skins.xml
plonetheme/office/profiles/default/theme.xml
plonetheme/office/skins/plonetheme_office/README.txt
plonetheme/office/static/README.md
plonetheme/office/static/README.txt
plonetheme/office/static/center-content.html
plonetheme/office/static/content.html
plonetheme/office/static/index.html
plonetheme/office/static/left-content.html
plonetheme/office/static/manifest.cfg
plonetheme/office/static/preview.png
plonetheme/office/static/right-content.html
plonetheme/office/static/rules.xml
plonetheme/office/static/bower_components/fastclick/.bower.json
plonetheme/office/static/bower_components/fastclick/LICENSE
plonetheme/office/static/bower_components/fastclick/README.md
plonetheme/office/static/bower_components/fastclick/bower.json
plonetheme/office/static/bower_components/fastclick/lib/fastclick.js
plonetheme/office/static/bower_components/foundation/.bower.json
plonetheme/office/static/bower_components/foundation/bower.json
plonetheme/office/static/bower_components/foundation/package.json
plonetheme/office/static/bower_components/foundation/css/foundation.css
plonetheme/office/static/bower_components/foundation/css/foundation.css.map
plonetheme/office/static/bower_components/foundation/css/foundation.min.css
