Metadata-Version: 1.1
Name: plonetheme.office
Version: 1.0
Summary: Plone Theme Office
Home-page: https://github.com/afterfivetech/plonetheme.office
Author: Afterfive Technologies
Author-email: afterfive2015@gmail.com
License: gpl
Download-URL: https://github.com/milktea/plonetheme.office/tarball/1.0
Keywords: testing,logging,example
Platform: UNKNOWN
Classifier: Framework :: Plone
Classifier: Programming Language :: Python
Classifier: Topic :: Software Development :: Libraries :: Python Modules
